setup.py
pydry/__init__.py
pydry/defaults.py
pydry/generic.py
pydry/string.py
pydry/text.py
python_pydry.egg-info/PKG-INFO
python_pydry.egg-info/SOURCES.txt
python_pydry.egg-info/dependency_links.txt
python_pydry.egg-info/requires.txt
python_pydry.egg-info/top_level.txt