Metadata-Version: 1.1
Name: python-pydry
Version: 0.0.2
Summary: A Python utility application that attempts to enforce DRY
Home-page: https://github.com/un33k/python-pydry
Author: Val Neekman
Author-email: info@neekware.com
License: BSD
Platform: UNKNOWN
Classifier: Development Status :: 3 - Alpha
Classifier: Intended Audience :: Developers
Classifier: License :: OSI Approved :: BSD License
Classifier: Operating System :: POSIX
Classifier: Programming Language :: Python
